blablatex/__init__.py
blablatex/cli.py
blablatex-1.1.1.dist-info/METADATA
blablatex-1.1.1.dist-info/WHEEL
blablatex-1.1.1.dist-info/entry_points.txt
blablatex-1.1.1.dist-info/RECORD
