Metadata-Version: 2.4
Name: BlaBlaTeX
Version: 1.1.1
Summary: CLI tool to manage and use your personal LaTeX templates
Project-URL: Repository, https://github.com/KasperNr1/BlaBlaTeX
Author-email: Matti Bos <matti.bos@gmx.de>
Requires-Python: >=3.7
Requires-Dist: gitpython
Requires-Dist: typer[all]
